hym16125/__init__.py
hym16125-1.0.dist-info/METADATA
hym16125-1.0.dist-info/WHEEL
hym16125-1.0.dist-info/top_level.txt
hym16125-1.0.dist-info/RECORD
